{
  "transactions": [
    {
      "id": 1,
      "description": "Desenvolvimento de site",
      "type": "income",
      "category": "Venda",
      "price": 14000,
      "createdAt": "2023-07-10T17:24:35.664Z"
    },
    {
      "id": 2,
      "description": "Hamburguer",
      "type": "outcome",
      "category": "Alimentação",
      "price": 60,
      "createdAt": "2023-07-10T17:22:35.664Z"
    },
    {
      "id": 3,
      "description": "Ignite Rocketseat",
      "type": "outcome",
      "category": "Educação",
      "price": 1980,
      "createdAt": "2023-06-28T17:22:35.664Z"
    },
    {
      "description": "suco de laranja",
      "price": 9,
      "category": "alimentação",
      "type": "outcome",
      "createdAt": "2023-07-10T21:25:16.421Z",
      "id": 4
    },
    {
      "description": "salario",
      "price": 8498.9,
      "category": "Trabalho",
      "type": "income",
      "createdAt": "2023-07-10T21:28:37.781Z",
      "id": 5
    }
  ]
}